antelop/__init__.py
antelop/analysis/__init__.py
antelop/analysis/firing_rate.py
antelop/analysis/hello_world.py
antelop/analysis/isi.py
antelop/analysis/sta.py
antelop/configs/.streamlit/config.toml
antelop/configs/.streamlit/credentials.toml
antelop/connection/__init__.py
antelop/connection/connect.py
antelop/connection/connect_utils.py
antelop/connection/import_schemas.py
antelop/connection/permission.py
antelop/connection/st_connect.py
antelop/connection/transaction.py
antelop/connection/utils.py
antelop/gui/__init__.py
antelop/gui/config.py
antelop/gui/export.py
antelop/gui/home.py
antelop/gui/nopermission.py
antelop/gui/search.py
antelop/gui/session.py
antelop/gui/admin/__init__.py
antelop/gui/admin/permanent_delete.py
antelop/gui/admin/release_computation.py
antelop/gui/admin/restore.py
antelop/gui/analysis/__init__.py
antelop/gui/analysis/analysis.py
antelop/gui/analysis/reproduce.py
antelop/gui/behaviour/__init__.py
antelop/gui/behaviour/add_features.py
antelop/gui/behaviour/define_rig.py
antelop/gui/behaviour/extract_kinematics.py
antelop/gui/behaviour/import_data.py
antelop/gui/behaviour/label_frames.py
antelop/gui/behaviour/recompute_masks.py
antelop/gui/behaviour/train_dlc.py
antelop/gui/ephys/__init__.py
antelop/gui/ephys/manual_curation.py
antelop/gui/ephys/probe_geometry.py
antelop/gui/ephys/probe_insertion.py
antelop/gui/ephys/schedule_spikesorting.py
antelop/gui/ephys/spikesorting_parameters.py
antelop/gui/ephys/upload_recording.py
antelop/gui/visualisation/kinematics.py
antelop/gui/visualisation/rasters.py
antelop/gui/visualisation/waveforms.py
antelop/load_connection/__init__.py
antelop/resources/behaviour.png
antelop/resources/ephys.png
antelop/resources/ephys_extensions.json
antelop/resources/session.png
antelop/resources/spikesorter_default_params.json
antelop/resources/spikesorter_descriptions.json
antelop/resources/spiketrain.png
antelop/resources/probes/LICENSE
antelop/resources/probes/README.md
antelop/resources/probes/tests.py
antelop-0.1.11.dist-info/METADATA
antelop-0.1.11.dist-info/WHEEL
antelop-0.1.11.dist-info/entry_points.txt
antelop-0.1.11.dist-info/licenses/LICENSE
antelop-0.1.11.dist-info/RECORD
