Metadata-Version: 2.4
Name: antelop
Version: 0.1.11
Summary: Antelop is a data management and processing tool for systems neuroscientists
Project-URL: Homepage, https://github.com/mtripodi/Antelop
License-File: LICENSE
Classifier: License :: OSI Approved :: MIT License
Classifier: Operating System :: OS Independent
Classifier: Programming Language :: Python :: 3.10
Requires-Python: ==3.10.*
Requires-Dist: datajoint==0.14.1
Requires-Dist: gitpython>=3.1.43
Requires-Dist: h5py<3.8
Requires-Dist: hdmf==3.14.5
Requires-Dist: ipython==8.18.1
Requires-Dist: joblib>=1.4.2
Requires-Dist: jsonschema==4.19.2
Requires-Dist: networkx<3.0
Requires-Dist: numpy==1.23.5
Requires-Dist: paramiko==3.3.1
Requires-Dist: pillow<10
Requires-Dist: probeinterface==0.2.19
Requires-Dist: pynwb==2.5.0
Requires-Dist: pyyaml==6.0.1
Requires-Dist: requests==2.32.3
Requires-Dist: tabulate>=0.9.0
Requires-Dist: toml==0.10.2
Provides-Extra: deeplabcut
Requires-Dist: deeplabcut[gui]>=3.0.0rc8; extra == 'deeplabcut'
Requires-Dist: protobuf==3.20.3; extra == 'deeplabcut'
Requires-Dist: scikit-image==0.19.1; extra == 'deeplabcut'
Provides-Extra: full
Requires-Dist: deeplabcut[gui]>=3.0.0rc8; extra == 'full'
Requires-Dist: phy-poetry==0.1.4; extra == 'full'
Requires-Dist: plotly==5.19.0; extra == 'full'
Requires-Dist: protobuf==3.20.3; extra == 'full'
Requires-Dist: scikit-image==0.19.1; extra == 'full'
Requires-Dist: streamlit-antd-components==0.3.2; extra == 'full'
Requires-Dist: streamlit==1.29.0; extra == 'full'
Requires-Dist: urllib3==2.0.7; extra == 'full'
Provides-Extra: gui
Requires-Dist: plotly==5.19.0; extra == 'gui'
Requires-Dist: streamlit-antd-components==0.3.2; extra == 'gui'
Requires-Dist: streamlit==1.29.0; extra == 'gui'
Requires-Dist: urllib3==2.0.7; extra == 'gui'
Provides-Extra: phy
Requires-Dist: phy-poetry==0.1.4; extra == 'phy'
